typepy/__init__.py
typepy/__version__.py
typepy/_common.py
typepy/_const.py
typepy/_function.py
typepy/_typecode.py
typepy/error.py
typepy/py.typed
typepy/checker/__init__.py
typepy/checker/_bool.py
typepy/checker/_bytes.py
typepy/checker/_checker.py
typepy/checker/_common.py
typepy/checker/_datetime.py
typepy/checker/_dictionary.py
typepy/checker/_infinity.py
typepy/checker/_integer.py
typepy/checker/_interface.py
typepy/checker/_ipaddress.py
typepy/checker/_list.py
typepy/checker/_nan.py
typepy/checker/_none.py
typepy/checker/_realnumber.py
typepy/checker/_string.py
typepy/converter/__init__.py
typepy/converter/_bool.py
typepy/converter/_bytes.py
typepy/converter/_datetime.py
typepy/converter/_dictionary.py
typepy/converter/_integer.py
typepy/converter/_interface.py
typepy/converter/_ipaddress.py
typepy/converter/_list.py
typepy/converter/_nop.py
typepy/converter/_realnumber.py
typepy/converter/_string.py
typepy/type/__init__.py
typepy/type/_base.py
typepy/type/_binary.py
typepy/type/_bool.py
typepy/type/_bytes.py
typepy/type/_datetime.py
typepy/type/_dictionary.py
typepy/type/_infinity.py
typepy/type/_integer.py
typepy/type/_ipaddress.py
typepy/type/_list.py
typepy/type/_nan.py
typepy/type/_none.py
typepy/type/_realnumber.py
typepy/type/_string.py
typepy-1.3.3.dist-info/LICENSE
typepy-1.3.3.dist-info/METADATA
typepy-1.3.3.dist-info/WHEEL
typepy-1.3.3.dist-info/top_level.txt
typepy-1.3.3.dist-info/RECORD
