Metadata-Version: 2.1
Name: typepy
Version: 1.3.3
Summary: typepy is a Python library for variable type checker/validator/converter at a run time.
Home-page: https://github.com/thombashi/typepy
Author: Tsuyoshi Hombashi
Author-email: tsuyoshi.hombashi@gmail.com
License: MIT License
Project-URL: Changelog, https://github.com/thombashi/typepy/releases
Project-URL: Documentation, https://typepy.rtfd.io/
Project-URL: Source, https://github.com/thombashi/typepy
Project-URL: Tracker, https://github.com/thombashi/typepy/issues
Keywords: library,type-checking,type-conversion,validator
Classifier: Development Status :: 5 - Production/Stable
Classifier: Intended Audience :: Developers
Classifier: Intended Audience :: Information Technology
Classifier: License :: OSI Approved :: MIT License
Classifier: Operating System :: OS Independent
Classifier: Programming Language :: Python :: 3
Classifier: Programming Language :: Python :: 3.9
Classifier: Programming Language :: Python :: 3.10
Classifier: Programming Language :: Python :: 3.11
Classifier: Programming Language :: Python :: 3.12
Classifier: Programming Language :: Python :: 3.13
Classifier: Programming Language :: Python :: 3 :: Only
Classifier: Programming Language :: Python :: Implementation :: CPython
Classifier: Programming Language :: Python :: Implementation :: PyPy
Classifier: Topic :: Software Development :: Libraries
Classifier: Topic :: Software Development :: Libraries :: Python Modules
Requires-Python: >=3.9
License-File: LICENSE
Requires-Dist: mbstrdecoder<2,>=1.0.0
Provides-Extra: datetime
Requires-Dist: python-dateutil<3.0.0,>=2.8.0; extra == "datetime"
Requires-Dist: pytz>=2018.9; extra == "datetime"
Requires-Dist: packaging; extra == "datetime"
Provides-Extra: test
Requires-Dist: pytest>=6.0.1; extra == "test"
Requires-Dist: tcolorpy; extra == "test"
Requires-Dist: python-dateutil<3.0.0,>=2.8.0; extra == "test"
Requires-Dist: pytz>=2018.9; extra == "test"
Requires-Dist: packaging; extra == "test"
